jsonpath_ng/__init__.py
jsonpath_ng/exceptions.py
jsonpath_ng/jsonpath.py
jsonpath_ng/lexer.py
jsonpath_ng/parser.py
jsonpath_ng/bin/__init__.py
jsonpath_ng/bin/jsonpath.py
jsonpath_ng/ext/__init__.py
jsonpath_ng/ext/arithmetic.py
jsonpath_ng/ext/filter.py
jsonpath_ng/ext/iterable.py
jsonpath_ng/ext/parser.py
jsonpath_ng/ext/string.py
dg_jsonpath_ng-1.7.2.dist-info/LICENSE
dg_jsonpath_ng-1.7.2.dist-info/METADATA
dg_jsonpath_ng-1.7.2.dist-info/WHEEL
dg_jsonpath_ng-1.7.2.dist-info/entry_points.txt
dg_jsonpath_ng-1.7.2.dist-info/top_level.txt
dg_jsonpath_ng-1.7.2.dist-info/RECORD
